launchpad_client/__init__.py
launchpad_client/_version.py
launchpad_client/const.py
launchpad_client/errors.py
launchpad_client/launchpad.py
launchpad_client/util.py
launchpad_client/models/__init__.py
launchpad_client/models/base.py
launchpad_client/models/project.py
launchpad_client/models/recipe.py
launchpad_client-0.1.0.dist-info/COPYING
launchpad_client-0.1.0.dist-info/METADATA
launchpad_client-0.1.0.dist-info/WHEEL
launchpad_client-0.1.0.dist-info/top_level.txt
launchpad_client-0.1.0.dist-info/RECORD
